[
    {
        "key": "dbln",
        "value": "%7B%2261555784965277%22%3A%22rC5RhDNS%22%2C%2261555499413093%22%3A%22Bbt2Pxa2%22%2C%2261555815587626%22%3A%22dvYxYRdZ%22%2C%22100035065897711%22%3A%22uIc40bqQ%22%2C%2261557513011069%22%3A%22GxKPrHQU%22%7D",
        "domain": "facebook.com",
        "path": "/login/device-based/",
        "hostOnly": false,
        "creation": "2024-06-22T10:03:40.034Z",
        "lastAccessed": "2024-06-22T10:03:40.034Z"
    },
    {
        "key": "sb",
        "value": "5_6_Zdjp3nIdmmnhjtmMp3TZ",
        "domain": "facebook.com",
        "path": "/",
        "hostOnly": false,
        "creation": "2024-06-22T10:03:40.034Z",
        "lastAccessed": "2024-06-22T10:03:40.034Z"
    },
    {
        "key": "datr",
        "value": "N0seZm06qynAsUmE4HzIzNZQ",
        "domain": "facebook.com",
        "path": "/",
        "hostOnly": false,
        "creation": "2024-06-22T10:03:40.034Z",
        "lastAccessed": "2024-06-22T10:03:40.034Z"
    },
    {
        "key": "ps_n",
        "value": "1",
        "domain": "facebook.com",
        "path": "/",
        "hostOnly": false,
        "creation": "2024-06-22T10:03:40.034Z",
        "lastAccessed": "2024-06-22T10:03:40.034Z"
    },
    {
        "key": "ps_l",
        "value": "1",
        "domain": "facebook.com",
        "path": "/",
        "hostOnly": false,
        "creation": "2024-06-22T10:03:40.034Z",
        "lastAccessed": "2024-06-22T10:03:40.034Z"
    },
    {
        "key": "locale",
        "value": "en_US",
[
    {
        "key": "dbln",
        "value": "%7B%2261555784965277%22%3A%22rC5RhDNS%22%2C%2261555499413093%22%3A%22Bbt2Pxa2%22%2C%2261555815587626%22%3A%22dvYxYRdZ%22%2C%22100035065897711%22%3A%22uIc40bqQ%22%2C%2261557513011069%22%3A%22GxKPrHQU%22%7D",
        "domain": "facebook.com",
        "path": "/login/device-based/",
        "hostOnly": false,
        "creation": "2024-06-22T10:03:40.034Z",
        "lastAccessed": "2024-06-22T10:03:40.034Z"
    },
    {
        "key": "sb",
        "value": "5_6_Zdjp3nIdmmnhjtmMp3TZ",
        "domain": "facebook.com",
        "path": "/",
        "hostOnly": false,
        "creation": "2024-06-22T10:03:40.034Z",
        "lastAccessed": "2024-06-22T10:03:40.034Z"
    },
    {
        "key": "datr",
        "value": "N0seZm06qynAsUmE4HzIzNZQ",
        "domain": "facebook.com",
        "path": "/",
        "hostOnly": false,
        "creation": "2024-06-22T10:03:40.034Z",
        "lastAccessed": "2024-06-22T10:03:40.034Z"
    },
    {
        "key": "ps_n",
        "value": "1",
        "domain": "facebook.com",
        "path": "/",
        "hostOnly": false,
        "creation": "2024-06-22T10:03:40.034Z",
        "lastAccessed": "2024-06-22T10:03:40.034Z"
    },
    {
        "key": "ps_l",
        "value": "1",
        "domain": "facebook.com",
        "path": "/",
        "hostOnly": false,
        "creation": "2024-06-22T10:03:40.034Z",
        "lastAccessed": "2024-06-22T10:03:40.034Z"
    },
    {
        "key": "locale",
        "value": "en_US",
        "domain": "facebook.com",
        "path": "/",
        "hostOnly": false,
        "creation": "2024-06-22T10:03:40.034Z",
        "lastAccessed": "2024-06-22T10:03:40.034Z"
    },
    {
        "key": "vpd",
        "value": "v1%3B723x384x1.875",
        "domain": "facebook.com",
        "path": "/",
        "hostOnly": false,
        "creation": "2024-06-22T10:03:40.034Z",
        "lastAccessed": "2024-06-22T10:03:40.034Z"
    },
    {
        "key": "m_pixel_ratio",
        "value": "1.875",
        "domain": "facebook.com",
        "path": "/",
        "hostOnly": false,
        "creation": "2024-06-22T10:03:40.034Z",
        "lastAccessed": "2024-06-22T10:03:40.034Z"
    },
    {
        "key": "wd",
        "value": "384x723",
        "domain": "facebook.com",
        "path": "/",
        "hostOnly": false,
        "creation": "2024-06-22T10:03:40.034Z",
        "lastAccessed": "2024-06-22T10:03:40.034Z"
    },
    {
        "key": "c_user",
        "value": "61557513011069",
        "domain": "facebook.com",
        "path": "/",
        "hostOnly": false,
        "creation": "2024-06-22T10:03:40.034Z",
        "lastAccessed": "2024-06-22T10:03:40.034Z"
    },
    {
        "key": "xs",
        "value": "33%3Ah0obplIRxUdBMQ%3A2%3A1719050610%3A-1%3A7281",
        "domain": "facebook.com",
        "path": "/",
        "hostOnly": false,
        "creation": "2024-06-22T10:03:40.034Z",
        "lastAccessed": "2024-06-22T10:03:40.034Z"
    },
    {
        "key": "oo",
        "value": "v1",
        "domain": "facebook.com",
        "path": "/",
        "hostOnly": false,
        "creation": "2024-06-22T10:03:40.034Z",
        "lastAccessed": "2024-06-22T10:03:40.035Z"
    },
    {
        "key": "wl_cbv",
        "value": "v2%3Bclient_version%3A2536%3Btimestamp%3A1719050613",
        "domain": "facebook.com",
        "path": "/",
        "hostOnly": false,
        "creation": "2024-06-22T10:03:40.035Z",
        "lastAccessed": "2024-06-22T10:03:40.035Z"
    },
    {
        "key": "fbl_st",
        "value": "101038378%3BT%3A28650843",
        "domain": "facebook.com",
        "path": "/",
        "hostOnly": false,
        "creation": "2024-06-22T10:03:40.035Z",
        "lastAccessed": "2024-06-22T10:03:40.035Z"
    }
]￼Enter        "domain": "facebook.com",
        "path": "/",
        "hostOnly": false,
        "creation": "2024-06-22T10:03:40.034Z",
        "lastAccessed": "2024-06-22T10:03:40.034Z"
    },
    {
        "key": "vpd",
        "value": "v1%3B723x384x1.875",
        "domain": "facebook.com",
        "path": "/",
        "hostOnly": false,
        "creation": "2024-06-22T10:03:40.034Z",
        "lastAccessed": "2024-06-22T10:03:40.034Z"
    },
    {
        "key": "m_pixel_ratio",
        "value": "1.875",
        "domain": "facebook.com",
        "path": "/",
        "hostOnly": false,
        "creation": "2024-06-22T10:03:40.034Z",
        "lastAccessed": "2024-06-22T10:03:40.034Z"
    },
    {
        "key": "wd",
  "value": "384x723",
        "domain": "facebook.com",
        "path": "/",
        "hostOnly": false,
        "creation": "2024-06-22T10:03:40.034Z",
        "lastAccessed": "2024-06-22T10:03:40.034Z"
    },
    {
        "key": "c_user",
        "value": "61557513011069",
        "domain": "facebook.com",
        "path": "/",
        "hostOnly": false,
        "creation": "2024-06-22T10:03:40.034Z",
        "lastAccessed": "2024-06-22T10:03:40.034Z"
    },
    {
        "key": "xs",
        "value": "33%3Ah0obplIRxUdBMQ%3A2%3A1719050610%3A-1%3A7281",
        "domain": "facebook.com",
        "path": "/",
        "hostOnly": false,
        "creation": "2024-06-22T10:03:40.034Z",
        "lastAccessed": "2024-06-22T10:03:40.034Z"
    },
    {
